implay/__init__.py
implay/main.py
implay-0.11.dist-info/METADATA
implay-0.11.dist-info/WHEEL
implay-0.11.dist-info/top_level.txt
implay-0.11.dist-info/RECORD
