Metadata-Version: 2.4
Name: implay
Version: 0.11
Home-page: https://subinek.com/
Author: subin erattakulangara
Requires-Dist: ipywidgets
Requires-Dist: opencv-python
Requires-Dist: IPython
Requires-Dist: numpy
Dynamic: author
Dynamic: description
Dynamic: description-content-type
Dynamic: home-page
Dynamic: requires-dist
